adataviz/__init__.py
adataviz/_version.py
adataviz/plotting.py
adataviz/tools.py
adataviz/utils.py
adataviz-0.1.dist-info/licenses/LICENSE
adataviz-0.1.dist-info/METADATA
adataviz-0.1.dist-info/WHEEL
adataviz-0.1.dist-info/entry_points.txt
adataviz-0.1.dist-info/top_level.txt
adataviz-0.1.dist-info/RECORD
