Metadata-Version: 2.4
Name: adataviz
Version: 0.1
Summary: A python package to visualize adata
Home-page: https://github.com/DingWB/adataviz
Author: Wubin Ding
Author-email: Wubin Ding <ding.wu.bin.gm@gmail.com>
License: MIT License
Project-URL: Homepage, https://github.com/DingWB/adataviz
Project-URL: repository, https://github.com/DingWB/adataviz
Project-URL: Bug Tracker, https://github.com/DingWB/adataviz/issues
Project-URL: documentation, https://dingwb.github.io/adataviz
Keywords: adata,visualization
Classifier: Programming Language :: Python :: 3
Classifier: License :: OSI Approved :: MIT License
Classifier: Operating System :: OS Independent
Requires-Python: >=3.0
License-File: LICENSE
Requires-Dist: matplotlib
Requires-Dist: numpy
Requires-Dist: pandas>=1.3.5
Requires-Dist: scipy
Requires-Dist: loguru
Requires-Dist: anndata
Requires-Dist: fire
Requires-Dist: scanpy
Requires-Dist: PyComplexHeatmap
Requires-Dist: seaborn
Requires-Dist: adjustText
Requires-Dist: plotly
Requires-Dist: ipywidgets
Dynamic: author
Dynamic: home-page
Dynamic: license-file
